mp2c/__init__.py
mp2c/context.py
mp2c/converter.py
mp2c/errors.py
mp2c/result.py
mp2c/rules.py
mp2c/utils.py
mp2c/visitors.py
test/__init__.py
test/test_array.py
test/test_comprehensive.py
test/test_control.py
test/test_lexical.py
test/test_math.py
test/test_scope.py
test/test_subprogram.py
test/test_visitors.py
mp2c-0.9.0.dist-info/METADATA
mp2c-0.9.0.dist-info/WHEEL
mp2c-0.9.0.dist-info/top_level.txt
mp2c-0.9.0.dist-info/RECORD
