Metadata-Version: 2.1
Name: mp2c
Version: 0.9.0
Summary: A Python package that convert MiniPascal code to C code
Requires-Dist: lark
